logsloth/__init__.py
logsloth/__main__.py
logsloth/common_import.py
logsloth/logsloth.py
logsloth/ls_color_selector.py
logsloth/ls_hook_base.py
logsloth-1.1.2.dist-info/licenses/LICENSE
logsloth-1.1.2.dist-info/METADATA
logsloth-1.1.2.dist-info/WHEEL
logsloth-1.1.2.dist-info/top_level.txt
logsloth-1.1.2.dist-info/RECORD
